{"otherData": {},"traceEvents":[{},{"cat":"function","dur":42244,"name":"glfwInit","ph":"X","pid":0,"tid":50712,"ts":307242455020.100},{"cat":"function","dur":212394,"name":"glfwCreateWindow","ph":"X","pid":0,"tid":50712,"ts":307242500107.600},{"cat":"function","dur":3812,"name":"void __cdecl Elys::OpenGLContext::Init(void)","ph":"X","pid":0,"tid":50712,"ts":307242712753.100},{"cat":"function","dur":49,"name":"void __cdecl Elys::WindowsWindow::SetVSync(bool)","ph":"X","pid":0,"tid":50712,"ts":307242741021.000},{"cat":"function","dur":287103,"name":"void __cdecl Elys::WindowsWindow::Init(const struct Elys::WindowProps &)","ph":"X","pid":0,"tid":50712,"ts":307242454150.100},{"cat":"function","dur":287247,"name":"__cdecl Elys::WindowsWindow::WindowsWindow(const struct Elys::WindowProps &)","ph":"X","pid":0,"tid":50712,"ts":307242454149.100},{"cat":"function","dur":27,"name":"void __cdecl Elys::OpenGLRendererAPI::Init(void)","ph":"X","pid":0,"tid":50712,"ts":307242741507.000},{"cat":"function","dur":4,"name":"__cdecl Elys::OpenGLVertexArray::OpenGLVertexArray(void)","ph":"X","pid":0,"tid":50712,"ts":307242741643.700},{"cat":"function","dur":28,"name":"__cdecl Elys::OpenGLVertexBuffer::OpenGLVertexBuffer(unsigned int)","ph":"X","pid":0,"tid":50712,"ts":307242741756.700},{"cat":"function","dur":1,"name":"void __cdecl Elys::OpenGLVertexBuffer::Bind(void) const","ph":"X","pid":0,"tid":50712,"ts":307242741902.900},{"cat":"function","dur":106,"name":"void __cdecl Elys::OpenGLVertexArray::AddVertexBuffer(const class std::shared_ptr<class Elys::VertexBuffer> &)","ph":"X","pid":0,"tid":50712,"ts":307242741901.300},{"cat":"function","dur":500,"name":"__cdecl Elys::OpenGLIndexBuffer::OpenGLIndexBuffer(unsigned int *,unsigned int)","ph":"X","pid":0,"tid":50712,"ts":307242742788.500},{"cat":"function","dur":1,"name":"void __cdecl Elys::OpenGLIndexBuffer::Bind(void) const","ph":"X","pid":0,"tid":50712,"ts":307242743777.900},{"cat":"function","dur":136,"name":"void __cdecl Elys::OpenGLVertexArray::SetIndexBuffer(const class std::shared_ptr<class Elys::IndexBuffer> &)","ph":"X","pid":0,"tid":50712,"ts":307242743773.900},{"cat":"function","dur":181,"name":"__cdecl Elys::OpenGLTexture2D::OpenGLTexture2D(unsigned int,unsigned int)","ph":"X","pid":0,"tid":50712,"ts":307242744036.700},{"cat":"function","dur":41,"name":"void __cdecl Elys::OpenGLTexture2D::SetData(void *,unsigned int)","ph":"X","pid":0,"tid":50712,"ts":307242744338.500},{"cat":"function","dur":177,"name":"class std::basic_string<char,struct std::char_traits<char>,class std::allocator<char> > __cdecl Elys::OpenGLShader::ReadFile(const class std::basic_string<char,struct std::char_traits<char>,class std::allocator<char> > &)","ph":"X","pid":0,"tid":50712,"ts":307242744515.500},{"cat":"function","dur":27,"name":"class std::unordered_map<unsigned int,class std::basic_string<char,struct std::char_traits<char>,class std::allocator<char> >,struct std::hash<unsigned int>,struct std::equal_to<unsigned int>,class std::allocator<struct std::pair<unsigned int const ,class std::basic_string<char,struct std::char_traits<char>,class std::allocator<char> > > > > __cdecl Elys::OpenGLShader::PreProcess(const class std::basic_string<char,struct std::char_traits<char>,class std::allocator<char> > &)","ph":"X","pid":0,"tid":50712,"ts":307242744805.600},{"cat":"function","dur":247,"name":"void __cdecl Elys::OpenGLShader::Compile(class std::unordered_map<unsigned int,class std::basic_string<char,struct std::char_traits<char>,class std::allocator<char> >,struct std::hash<unsigned int>,struct std::equal_to<unsigned int>,class std::allocator<struct std::pair<unsigned int const ,class std::basic_string<char,struct std::char_traits<char>,class std::allocator<char> > > > > &)","ph":"X","pid":0,"tid":50712,"ts":307242744935.500},{"cat":"function","dur":781,"name":"__cdecl Elys::OpenGLShader::OpenGLShader(const class std::basic_string<char,struct std::char_traits<char>,class std::allocator<char> > &)","ph":"X","pid":0,"tid":50712,"ts":307242744514.300},{"cat":"function","dur":9,"name":"void __cdecl Elys::OpenGLShader::Bind(void) const","ph":"X","pid":0,"tid":50712,"ts":307242745395.800},{"cat":"function","dur":3928,"name":"void __cdecl Elys::Renderer2D::Init(void)","ph":"X","pid":0,"tid":50712,"ts":307242741636.600},{"cat":"function","dur":4154,"name":"void __cdecl Elys::Renderer::Init(void)","ph":"X","pid":0,"tid":50712,"ts":307242741506.300},{"cat":"function","dur":233,"name":"void __cdecl Elys::ImGuiLayer::OnAttach(void)","ph":"X","pid":0,"tid":50712,"ts":307242745757.900},{"cat":"function","dur":334,"name":"void __cdecl Elys::Application::PushOverlay(class Elys::Layer *)","ph":"X","pid":0,"tid":50712,"ts":307242745754.200},{"cat":"function","dur":292039,"name":"__cdecl Elys::Application::Application(void)","ph":"X","pid":0,"tid":50712,"ts":307242454140.300},{"cat":"function","dur":2,"name":"__cdecl Elys::OrthographicCamera::OrthographicCamera(float,float,float,float)","ph":"X","pid":0,"tid":50712,"ts":307242746276.600},{"cat":"function","dur":192,"name":"stbi_load - OpenGLTexture2D::OpenGLTexture2D(const std::string&)","ph":"X","pid":0,"tid":50712,"ts":307242746381.200},{"cat":"function","dur":538,"name":"__cdecl Elys::OpenGLTexture2D::OpenGLTexture2D(const class std::basic_string<char,struct std::char_traits<char>,class std::allocator<char> > &)","ph":"X","pid":0,"tid":50712,"ts":307242746380.200},{"cat":"function","dur":32196,"name":"Init Grid","ph":"X","pid":0,"tid":50712,"ts":307242747165.500},{"cat":"function","dur":33194,"name":"void __cdecl Sandbox2D::OnAttach(void)","ph":"X","pid":0,"tid":50712,"ts":307242746375.700},{"cat":"function","dur":33342,"name":"void __cdecl Elys::Application::PushLayer(class Elys::Layer *)","ph":"X","pid":0,"tid":50712,"ts":307242746372.600}]}